ddcci_plasmoid_backend/Node.py
ddcci_plasmoid_backend/Node_test.py
ddcci_plasmoid_backend/__init__.py
ddcci_plasmoid_backend/__main__.py
ddcci_plasmoid_backend/ddcci.py
ddcci_plasmoid_backend/ddcci_test.py
ddcci_plasmoid_backend-0.1.10.dist-info/METADATA
ddcci_plasmoid_backend-0.1.10.dist-info/WHEEL
ddcci_plasmoid_backend-0.1.10.dist-info/entry_points.txt
ddcci_plasmoid_backend-0.1.10.dist-info/RECORD
