Metadata-Version: 2.1
Name: ddcci-plasmoid-backend
Version: 0.1.10
Summary: Backend for ddcci-plasmoid
Home-page: https://github.com/davidhi7/ddcci-plasmoid
License: MIT
Keywords: ddcci,brightmess,widget,kde,plasma
Author: David Himmelstoß
Author-email: 77309510+davidhi7@users.noreply.github.com
Requires-Python: >=3.8,<4.0
Classifier: Environment :: X11 Applications :: KDE
Classifier: License :: OSI Approved :: MIT License
Classifier: Programming Language :: Python :: 3
Classifier: Programming Language :: Python :: 3.8
Classifier: Programming Language :: Python :: 3.9
Classifier: Programming Language :: Python :: 3.10
Classifier: Programming Language :: Python :: 3.11
Classifier: Programming Language :: Python :: 3.12
Classifier: Topic :: Desktop Environment :: K Desktop Environment (KDE)
Classifier: Topic :: System :: Hardware
Requires-Dist: fasteners (>=0.18,<0.19)
Project-URL: Repository, https://github.com/davidhi7/ddcci-plasmoid
